pyfakeuse/__init__.py
pyfakeuse/pyfakeuse.py
pyfakeuse/static.py
pyfakeuse-0.0.9.dist-info/LICENSE
pyfakeuse-0.0.9.dist-info/METADATA
pyfakeuse-0.0.9.dist-info/WHEEL
pyfakeuse-0.0.9.dist-info/top_level.txt
pyfakeuse-0.0.9.dist-info/RECORD
