Metadata-Version: 2.1
Name: pyfakeuse
Version: 0.0.9
Summary: pyfakeuse helps you fool development environments and code inspectors
Home-page: https://veltzer.github.io/pyfakeuse
Download-URL: https://github.com/veltzer/pyfakeuse
Author: Mark Veltzer
Author-email: mark.veltzer@gmail.com
Maintainer: Mark Veltzer
Maintainer-email: mark.veltzer@gmail.com
License: MIT
Keywords: python,fake,use,variables,idea,pycharm,fool
Platform: python3
Classifier: Development Status :: 4 - Beta
Classifier: Environment :: Console
Classifier: Operating System :: OS Independent
Classifier: Programming Language :: Python
Classifier: Programming Language :: Python :: 3
Classifier: Programming Language :: Python :: 3 :: Only
Classifier: Programming Language :: Python :: 3.11
Classifier: Topic :: Utilities
Classifier: License :: OSI Approved :: MIT License
License-File: LICENSE
